tkinter_fonts_viewer/__init__.py
tkinter_fonts_viewer/tkinter_fonts_viewer.py
tkinter_fonts_viewer/fonts/fonts_status.json
tkinter_fonts_viewer-0.1.2.dist-info/LICENSE.txt
tkinter_fonts_viewer-0.1.2.dist-info/METADATA
tkinter_fonts_viewer-0.1.2.dist-info/WHEEL
tkinter_fonts_viewer-0.1.2.dist-info/entry_points.txt
tkinter_fonts_viewer-0.1.2.dist-info/top_level.txt
tkinter_fonts_viewer-0.1.2.dist-info/RECORD
