Metadata-Version: 2.1
Name: tkinter-fonts-viewer
Version: 0.1.2
Summary: gui viewer for tkinter fonts
Home-page: https://github.com/streanger/tkinter_fonts_viewer
Author: streanger
Author-email: divisionexe@gmail.com
License: MIT
Keywords: tkinter fonts font viewer
Platform: UNKNOWN
Classifier: Programming Language :: Python :: 3
Classifier: License :: OSI Approved :: MIT License
Classifier: Operating System :: OS Independent
Requires-Python: >=3.5
